miwa_package_esi_sba/init.py
miwa_package_esi_sba/linreg.py
miwa_package_esi_sba-1.0.0.dist-info/LICENSE.txt
miwa_package_esi_sba-1.0.0.dist-info/METADATA
miwa_package_esi_sba-1.0.0.dist-info/WHEEL
miwa_package_esi_sba-1.0.0.dist-info/top_level.txt
miwa_package_esi_sba-1.0.0.dist-info/RECORD
