Metadata-Version: 2.1
Name: miwa-package-esi-sba
Version: 1.0.0
Summary: An awesome package that does something
Home-page: http://pypi.python.org/pypi/miwa_package_esi_sba/
Author: marouabel
Author-email: m.belmiloud@esi-sba.dz
License: LICENSE.txt
License-File: LICENSE.txt
Requires-Dist: miwa-package-esi-sba
